noire/__init__.py
noire/constants.py
noire/noire.py
noire/models/__init__.py
noire/models/membership.py
noire/models/moderation.py
noire/models/settings.py
noire/parsers/__init__.py
noire/parsers/members_list.py
noire/parsers/moderation.py
noire/parsers/settings.py
noire-0.5.0.dist-info/LICENSE
noire-0.5.0.dist-info/METADATA
noire-0.5.0.dist-info/WHEEL
noire-0.5.0.dist-info/top_level.txt
noire-0.5.0.dist-info/RECORD
